LICENSE
MANIFEST.in
README.md
requirements.txt
setup.cfg
setup.py
versioneer.py
ads_deploy/__init__.py
ads_deploy/__main__.py
ads_deploy/_version.py
ads_deploy/caproto_ioc.py
ads_deploy/config.py
ads_deploy/docs.py
ads_deploy/iocboot.py
ads_deploy/tsproj.py
ads_deploy/typhos_gui.py
ads_deploy/util.py
ads_deploy.egg-info/PKG-INFO
ads_deploy.egg-info/SOURCES.txt
ads_deploy.egg-info/dependency_links.txt
ads_deploy.egg-info/entry_points.txt
ads_deploy.egg-info/requires.txt
ads_deploy.egg-info/top_level.txt
ads_deploy/templates/__init__.py
ads_deploy/templates/index.rst
ads_deploy/templates/util.macro
ads_deploy/templates/{{tsproj.name}}_boxes.rst
ads_deploy/templates/{{tsproj.name}}_links.rst
ads_deploy/templates/{{tsproj.name}}_nc.rst
ads_deploy/templates/{{tsproj.name}}_pragmas.rst
ads_deploy/templates/{{tsproj.name}}_{{plc.name}}_epics.rst
ads_deploy/templates/{{tsproj.name}}_{{plc.name}}_source.rst
ads_deploy/templates/{{tsproj.name}}_{{plc.name}}_summary.rst
ads_deploy/tests/__init__.py
ads_deploy/tests/conftest.py
ads_deploy/tests/test_deploy.py
ads_deploy/windows/__init__.py
ads_deploy/windows/make_scripts.py
docs/Makefile
docs/make.bat
docs/source/conf.py
docs/source/index.rst