Metadata-Version: 2.1
Name: ads-deploy
Version: 2.11.1
Summary: TwinCAT ADS EPICS IOC deployment tools
Home-page: https://github.com/pcdshub/ads-deploy
Author: SLAC National Accelerator Laboratory
License: BSD
Platform: UNKNOWN
Classifier: Development Status :: 2 - Pre-Alpha
Classifier: Natural Language :: English
Classifier: Programming Language :: Python :: 3
